revolution/__init__.py
revolution/__main__.py
revolution/application.py
revolution/data.py
revolution/display.py
revolution/environment.py
revolution/motor.py
revolution/py.typed
revolution/steering_wheel.py
blueskysolarracing_revolution-0.0.0.dev0.dist-info/LICENSE
blueskysolarracing_revolution-0.0.0.dev0.dist-info/METADATA
blueskysolarracing_revolution-0.0.0.dev0.dist-info/WHEEL
blueskysolarracing_revolution-0.0.0.dev0.dist-info/top_level.txt
blueskysolarracing_revolution-0.0.0.dev0.dist-info/RECORD
